__init__.py
neuroxai/__init__.py
neuroxai/explanation.py
neuroxai/utils.py
neuroxai-0.0.0.4.dist-info/LICENSE
neuroxai-0.0.0.4.dist-info/METADATA
neuroxai-0.0.0.4.dist-info/WHEEL
neuroxai-0.0.0.4.dist-info/top_level.txt
neuroxai-0.0.0.4.dist-info/RECORD
