Metadata-Version: 2.1
Name: neuroxai
Version: 0.0.0.4
Summary: NeuroXAI: Adaptive, robust, explainable surrogate framework for determination of channel importance in EEG application
Home-page: https://github.com/dlcjfgmlnasa/NeuroXAI
Author: Cheol-Hui Lee
Author-email: dlcjfgmlnasa28@korea.ac.kr
License: Apache License 2.0
Requires-Python: >=3.5
License-File: LICENSE
Requires-Dist: lime
Requires-Dist: mne>=1.8.0
